{
    "2622": {
        "small": 486,
        "medium": 1032,
        "large": 1098,
        "left": 87,
        "right": 633,
        "top": 261,
        "middle": 873,
        "bottom": 1485
    },
    "2868": {
        "small": 510,
        "medium": 1092,
        "large": 1146,
        "left": 114,
        "right": 696,
        "top": 276,
        "middle": 912,
        "bottom": 1548
    },
    "2796": {
        "small": 510,
        "medium": 1092,
        "large": 1146,
        "left": 99,
        "right": 681,
        "top": 252,
        "middle": 888,
        "bottom": 1554
    },
    "2556": {
        "small": 474,
        "medium": 1014,
        "large": 1062,
        "left": 82,
        "right": 622,
        "top": 240,
        "middle": 828,
        "bottom": 1446
    },
    "2778": {
        "small": 510,
        "medium": 1092,
        "large": 1146,
        "left": 96,
        "right": 678,
        "top": 216,
        "middle": 852,
        "bottom": 1518
    },
    "2532": {
        "small": 474,
        "medium": 1014,
        "large": 1062,
        "left": 78,
        "right": 618,
        "top": 201,
        "middle": 789,
        "bottom": 1407
    },
    "2688": {
        "small": 507,
        "medium": 1080,
        "large": 1137,
        "left": 81,
        "right": 654,
        "top": 198,
        "middle": 828,
        "bottom": 1488
    },
    "1792": {
        "small": 338,
        "medium": 720,
        "large": 758,
        "left": 55,
        "right": 437,
        "top": 129,
        "middle": 549,
        "bottom": 999
    },
    "2208": {
        "small": 471,
        "medium": 1044,
        "large": 1071,
        "left": 99,
        "right": 672,
        "top": 84,
        "middle": 666,
        "bottom": 1278
    },
    "1334": {
        "small": 296,
        "medium": 642,
        "large": 648,
        "left": 54,
        "right": 400,
        "top": 30,
        "middle": 382,
        "bottom": 764
    },
    "1136": {
        "small": 282,
        "medium": 584,
        "large": 622,
        "left": 30,
        "right": 332,
        "top": 29,
        "middle": 369,
        "bottom": 399
    },
    "1624": {
        "small": 310,
        "medium": 658,
        "large": 690,
        "left": 46,
        "right": 394,
        "top": 112,
        "middle": 492,
        "bottom": 902
    },
    "2001": {
        "small": 444,
        "medium": 963,
        "large": 972,
        "left": 81,
        "right": 600,
        "top": 60,
        "middle": 588,
        "bottom": 1146
    },
    "2436x": {
        "small": 465,
        "medium": 987,
        "large": 1035,
        "left": 69,
        "right": 591,
        "top": 183,
        "middle": 753,
        "bottom": 1353
    },
    "2436mini": {
        "small": 465,
        "medium": 987,
        "large": 1035,
        "left": 69,
        "right": 591,
        "top": 201,
        "middle": 771,
        "bottom": 1371
    }
}
